circuit.v
`timescale 1ns / 1ps
`include "iob_lib.vh"

module circuit
  #(
  	parameter W=32
   )
  
  (
   `INPUT(rst,1),
   `INPUT(clk,1),
   `INPUT(en,1),
   `INPUT(X,W),
   `OUTPUT(Y,W)
   );

   `SIGNAL(new_max, W)
   `SIGNAL(max, W)
   `SIGNAL2OUT(Y, new_max)
   `SIGNAL(cnt,7)
   
   `REG_RE(clk,rst,1'b0,en & cnt!=99,max,new_max)
   
   `COUNTER_RE(clk, rst, cnt!=99, cnt)
   
   `COMB begin
   	if (X>max) new_max=X;
    end
   
   
   
endmodule

circuit_tb.v
`timescale 1ns / 1ps
`include "iob_lib.vh"

`define W 96

module circuit_tb;

   `CLOCK(clk, 10)
   `RESET(rst, 1, 10)
   `SIGNAL(en, 1)
   `SIGNAL(x,`W)
   `SIGNAL_OUT(y, `W)
   

   integer i,seed;
   
   initial begin
      seed=7;
      $dumpfile("circuit.vcd");
      $dumpvars();
      en=0;
      for (i=0; i<100; i=i+1) begin
      	x=$urandom(seed);
        @(posedge clk) #1 en=1;$display("%d %d",x,y);
      end

      @(posedge clk) #100 $finish;

   end 

   circuit
     #(
       .W(`W)
       ) 
   c0
     (
      .rst(rst),
      .clk(clk),
      .en(en),
      .X(x),
      .Y(y)
      );


endmodule

circuit.vcd
$date
	Tue Nov 17 22:43:49 2020
$end
$version
	Icarus Verilog
$end
$timescale
	1ps
$end
$scope module circuit_tb $end
$var wire 96 ! y [95:0] $end
$var reg 1 " clk $end
$var reg 1 # en $end
$var reg 1 $ rst $end
$var reg 96 % x [95:0] $end
$var integer 32 & i [31:0] $end
$var integer 32 ' seed [31:0] $end
$scope module c0 $end
$var wire 96 ( X [95:0] $end
$var wire 96 ) Y [95:0] $end
$var wire 1 " clk $end
$var wire 1 # en $end
$var wire 1 $ rst $end
$var reg 7 * cnt [6:0] $end
$var reg 96 + max [95:0] $end
$var reg 96 , new_max [95:0] $end
$upscope $end
$upscope $end
$enddefinitions $end
#0
$dumpvars
bx ,
bx +
bx *
bx )
b1110110001000000000 (
b1110110000010011100 '
b0 &
b1110110001000000000 %
0$
0#
1"
bx !
$end
#1000
1$
#5000
0"
#10000
b1110110001000000000 !
b1110110001000000000 )
b1110110001000000000 ,
b0 *
b0 +
1"
#11000
b11000110011011000100101110001100 !
b11000110011011000100101110001100 )
b11000110011011000100101110001100 ,
b11000110011011000100101110001100 %
b11000110011011000100101110001100 (
b11000110011011000100100011101101 '
b1 &
1#
0$
#15000
0"
#20000
b11000110011011000100101110001100 +
b1 *
1"
#21000
b10101101010101110111000101011010 %
b10101101010101110111000101011010 (
b10101101010101110110111011001010 '
b10 &
#25000
0"
#30000
b10 *
1"
#31000
b10101110011011011111101101011100 %
b10101110011011011111101101011100 (
b10101110011011011111100111000011 '
b11 &
#35000
0"
#40000
b11 *
1"
#41000
b111101100000101110101001111011 %
b111101100000101110101001111011 (
b111101100000101110100000101000 '
b100 &
#45000
0"
#50000
b100 *
1"
#51000
b11001111110001011111001110011111 !
b11001111110001011111001110011111 )
b11001111110001011111001110011111 ,
b11001111110001011111001110011111 %
b11001111110001011111001110011111 (
b11001111110001011111000000001001 '
b101 &
#55000
0"
#60000
b11001111110001011111001110011111 +
b101 *
1"
#61000
b1011110101110101010111010111101 %
b1011110101110101010111010111101 (
b1011110101110101010110000110110 '
b110 &
#65000
0"
#70000
b110 *
1"
#71000
b10011100001010011000000100 %
b10011100001010011000000100 (
b10011100001010010100111111 '
b111 &
#75000
0"
#80000
b111 *
1"
#81000
b1010001110101111000100010100011 %
b1010001110101111000100010100011 (
b1010001110101111000011001110100 '
b1000 &
#85000
0"
#90000
b1000 *
1"
#91000
b1110111101001000000000011 %
b1110111101001000000000011 (
b1110111101000111011100101 '
b1001 &
#95000
0"
#100000
b1001 *
1"
#101000
b1011011010111110001000010110110 %
b1011011010111110001000010110110 (
b1011011010111110000111001100010 '
b1010 &
#105000
0"
#110000
b1010 *
1"
#111000
b1101001110111000000000011010 %
b1101001110111000000000011010 (
b1101001110110111111001111011 '
b1011 &
#115000
0"
#120000
b1011 *
1"
#121000
b11100100010111000100000111001 %
b11100100010111000100000111001 (
b11100100010111000011110000000 '
b1100 &
#125000
0"
#130000
b1100 *
1"
#131000
b1111001000111010000001011110010 %
b1111001000111010000001011110010 (
b1111001000111010000000110000001 '
b1101 &
#135000
0"
#140000
b1101 *
1"
#141000
b1110110110011101100001011101101 %
b1110110110011101100001011101101 (
b1110110110011101100000101001110 '
b1110 &
#145000
0"
#150000
b1110 *
1"
#151000
b1100100101011111100001011001001 %
b1100100101011111100001011001001 (
b1100100101011111100000101110111 '
b1111 &
#155000
0"
#160000
b1111 *
1"
#161000
b1001111000001111111100010011110 %
b1001111000001111111100010011110 (
b1001111000001111111011101001100 '
b10000 &
#165000
0"
#170000
b10000 *
1"
#171000
b10101000001110111110010101010000 %
b10101000001110111110010101010000 (
b10101000001110111110001111011101 '
b10001 &
#175000
0"
#180000
b10001 *
1"
#181000
b10100110011001001011001101001100 %
b10100110011001001011001101001100 (
b10100110011001001011000011111010 '
b10010 &
#185000
0"
#190000
b10010 *
1"
#191000
b1100100110000110110000011001 %
b1100100110000110110000011001 (
b1100100110000110101000110011 '
b10011 &
#195000
0"
#200000
b10011 *
1"
#201000
b111101101001001010001001111011 %
b111101101001001010001001111011 (
b111101101001001010000111011000 '
b10100 &
#205000
0"
#210000
b10100 *
1"
#211000
b1011010111001011001001010110101 %
b1011010111001011001001010110101 (
b1011010111001011001000111111001 '
b10101 &
#215000
0"
#220000
b10101 *
1"
#221000
b100001110001000101000001000 %
b100001110001000101000001000 (
b100001110001000100101100110 '
b10110 &
#225000
0"
#230000
b10110 *
1"
#231000
b11001001101001100011011110010011 %
b11001001101001100011011110010011 (
b11001001101001100011010010101111 '
b10111 &
#235000
0"
#240000
b10111 *
1"
#241000
b11111011101000001010000111110 %
b11111011101000001010000111110 (
b11111011101000001001100100100 '
b11000 &
#245000
0"
#250000
b11000 *
1"
#251000
b101000000100000010100001010000 %
b101000000100000010100001010000 (
b101000000100000010011111010101 '
b11001 &
#255000
0"
#260000
b11001 *
1"
#261000
b1110110010101011100000011101 %
b1110110010101011100000011101 (
b1110110010101011011010010010 '
b11010 &
#265000
0"
#270000
b11010 *
1"
#271000
b11011010001010111001111110110100 !
b11011010001010111001111110110100 )
b11011010001010111001111110110100 ,
b11011010001010111001111110110100 %
b11011010001010111001111110110100 (
b11011010001010111001110011101011 '
b11011 &
#275000
0"
#280000
b11011010001010111001111110110100 +
b11011 *
1"
#281000
b10001000110011111001100100010001 %
b10001000110011111001100100010001 (
b10001000110011111001011100110000 '
b11100 &
#285000
0"
#290000
b11100 *
1"
#291000
b10110000000110011000001101100000 %
b10110000000110011000001101100000 (
b10110000000110011000000101110001 '
b11101 &
#295000
0"
#300000
b11101 *
1"
#301000
b11010001011100000110011110100010 %
b11010001011100000110011110100010 (
b11010001011100000110010001111110 '
b11110 &
#305000
0"
#310000
b11110 *
1"
#311000
b11010000100110001110000110100001 %
b11010000100110001110000110100001 (
b11010000100110001101111011100111 '
b11111 &
#315000
0"
#320000
b11111 *
1"
#321000
b10101100101000110011101101011001 %
b10101100101000110011101101011001 (
b10101100101000110011100111111100 '
b100000 &
#325000
0"
#330000
b100000 *
1"
#331000
b11000010101000110011110110000101 %
b11000010101000110011110110000101 (
b11000010101000110011101011001101 '
b100001 &
#335000
0"
#340000
b100001 *
1"
#341000
b1100001011111111000000011000010 %
b1100001011111111000000011000010 (
b1100001011111110111111100101010 '
b100010 &
#345000
0"
#350000
b100010 *
1"
#351000
b1011101101111111100000010111 %
b1011101101111111100000010111 (
b1011101101111111011010100011 '
b100011 &
#355000
0"
#360000
b100011 *
1"
#361000
b10110000011110011100100101100000 %
b10110000011110011100100101100000 (
b10110000011110011100011110001000 '
b100100 &
#365000
0"
#370000
b100100 *
1"
#371000
b1001000001011101011000010010000 %
b1001000001011101011000010010000 (
b1001000001011101010111111101001 '
b100101 &
#375000
0"
#380000
b100101 *
1"
#381000
b11011100001110101011010110111000 !
b11011100001110101011010110111000 )
b11011100001110101011010110111000 ,
b11011100001110101011010110111000 %
b11011100001110101011010110111000 (
b11011100001110101011001010010110 '
b100110 &
#385000
0"
#390000
b100110 *
b11011100001110101011010110111000 +
1"
#391000
b1000101010001010001000010001 %
b1000101010001010001000010001 (
b1000101010001010000000011111 '
b100111 &
#395000
0"
#400000
b100111 *
1"
#401000
b11111010010001100110000111110 %
b11111010010001100110000111110 (
b11111010010001100101111010100 '
b101000 &
#405000
0"
#410000
b101000 *
1"
#411000
b10001011011110001111111100010110 %
b10001011011110001111111100010110 (
b10001011011110001111110011000101 '
b101001 &
#415000
0"
#420000
b101001 *
1"
#421000
b11010001011111010110110110100010 %
b11010001011111010110110110100010 (
b11010001011111010110101011000010 '
b101010 &
#425000
0"
#430000
b101010 *
1"
#431000
b10001010100111000101100100010101 %
b10001010100111000101100100010101 (
b10001010100111000101011101011011 '
b101011 &
#435000
0"
#440000
b101011 *
1"
#441000
b1000110111111001001010010001101 %
b1000110111111001001010010001101 (
b1000110111111001001001011100000 '
b101100 &
#445000
0"
#450000
b101100 *
1"
#451000
b111110100101101111111001111101 %
b111110100101101111111001111101 (
b111110100101101111110101100001 '
b101101 &
#455000
0"
#460000
b101101 *
1"
#461000
b11000111001001111101010110001110 %
b11000111001001111101010110001110 (
b11000111001001111101001110101110 '
b101110 &
#465000
0"
#470000
b101110 *
1"
#471000
b1010100010100100101101010101000 %
b1010100010100100101101010101000 (
b1010100010100100101100001010111 '
b101111 &
#475000
0"
#480000
b101111 *
1"
#481000
b1100110001000010101000011001 %
b1100110001000010101000011001 (
b1100110001000010100010101100 '
b110000 &
#485000
0"
#490000
b110000 *
1"
#491000
b1010111110100010100111010101111 %
b1010111110100010100111010101111 (
b1010111110100010100110110111101 '
b110001 &
#495000
0"
#500000
b110001 *
1"
#501000
b1000001010010101101101010000010 %
b1000001010010101101101010000010 (
b1000001010010101101100101011010 '
b110010 &
#505000
0"
#510000
b110010 *
1"
#511000
b11101111010100111010000111011110 !
b11101111010100111010000111011110 )
b11101111010100111010000111011110 ,
b11101111010100111010000111011110 %
b11101111010100111010000111011110 (
b11101111010100111001111100010011 '
b110011 &
#515000
0"
#520000
b11101111010100111010000111011110 +
b110011 *
1"
#521000
b10000100000111010101101100001000 %
b10000100000111010101101100001000 (
b10000100000111010101100100111000 '
b110100 &
#525000
0"
#530000
b110100 *
1"
#531000
b10100010010000000100101101000100 %
b10100010010000000100101101000100 (
b10100010010000000100100111011001 '
b110101 &
#535000
0"
#540000
b110101 *
1"
#541000
b1111011000101000010100011110110 %
b1111011000101000010100011110110 (
b1111011000101000010011111000110 '
b110110 &
#545000
0"
#550000
b110110 *
1"
#551000
b10111100111011101110100101111001 %
b10111100111011101110100101111001 (
b10111100111011101110011110001111 '
b110111 &
#555000
0"
#560000
b110111 *
1"
#561000
b1010100101000001011001010101001 %
b1010100101000001011001010101001 (
b1010100101000001011000010000100 '
b111000 &
#565000
0"
#570000
b111000 *
1"
#571000
b10011110001010000000111100111100 %
b10011110001010000000111100111100 (
b10011110001010000000110110110101 '
b111001 &
#575000
0"
#580000
b111001 *
1"
#581000
b10111100011110100010110101111000 %
b10111100011110100010110101111000 (
b10111100011110100010101011110010 '
b111010 &
#585000
0"
#590000
b111010 *
1"
#591000
b1001100111101001010111010011001 %
b1001100111101001010111010011001 (
b1001100111101001010110111001011 '
b111011 &
#595000
0"
#600000
b111011 *
1"
#601000
b10111010100011010111110101110101 %
b10111010100011010111110101110101 (
b10111010100011010111101010010000 '
b111100 &
#605000
0"
#610000
b111100 *
1"
#611000
b1101000101000111011000011010 %
b1101000101000111011000011010 (
b1101000101000111010101010001 '
b111101 &
#615000
0"
#620000
b111101 *
1"
#621000
b11111000101010000001000111110001 !
b11111000101010000001000111110001 )
b11111000101010000001000111110001 ,
b11111000101010000001000111110001 %
b11111000101010000001000111110001 (
b11111000101010000000111011011110 '
b111110 &
#625000
0"
#630000
b111110 *
b11111000101010000001000111110001 +
1"
#631000
b10110110001100110010111101101100 %
b10110110001100110010111101101100 (
b10110110001100110010110111000111 '
b111111 &
#635000
0"
#640000
b111111 *
1"
#641000
b10101110000101011100010101011100 %
b10101110000101011100010101011100 (
b10101110000101011100001101011100 '
b1000000 &
#645000
0"
#650000
b1000000 *
1"
#651000
b1000101101101010001111010001011 %
b1000101101101010001111010001011 (
b1000101101101010001110010101101 '
b1000001 &
#655000
0"
#660000
b1000001 *
1"
#661000
b100001001010011100000001000010 %
b100001001010011100000001000010 (
b100001001010011011111110001010 '
b1000010 &
#665000
0"
#670000
b1000010 *
1"
#671000
b1101100101100100110010011011001 %
b1101100101100100110010011011001 (
b1101100101100100110001110000011 '
b1000011 &
#675000
0"
#680000
b1000011 *
1"
#681000
b1111101011010100101100011111010 %
b1111101011010100101100011111010 (
b1111101011010100101011011101000 '
b1000100 &
#685000
0"
#690000
b1000100 *
1"
#691000
b101011011110010110000001010110 %
b101011011110010110000001010110 (
b101011011110010101111111001001 '
b1000101 &
#695000
0"
#700000
b1000101 *
1"
#701000
b1011001110101111110101010110011 %
b1011001110101111110101010110011 (
b1011001110101111110100011110110 '
b1000110 &
#705000
0"
#710000
b1000110 *
1"
#711000
b11010001101100000000110110100011 %
b11010001101100000000110110100011 (
b11010001101100000000101011111111 '
b1000111 &
#715000
0"
#720000
b1000111 *
1"
#721000
b11100101100001101100001111001011 %
b11100101100001101100001111001011 (
b11100101100001101100000100110100 '
b1001000 &
#725000
0"
#730000
b1001000 *
1"
#731000
b1100101111011000101110011001011 %
b1100101111011000101110011001011 (
b1100101111011000101101010100101 '
b1001001 &
#735000
0"
#740000
b1001001 *
1"
#741000
b11111001100000111111100111110011 !
b11111001100000111111100111110011 )
b11111001100000111111100111110011 ,
b11111001100000111111100111110011 %
b11111001100000111111100111110011 (
b11111001100000111111011100100010 '
b1001010 &
#745000
0"
#750000
b1001010 *
b11111001100000111111100111110011 +
1"
#751000
b1111001010110111010001011110010 %
b1111001010110111010001011110010 (
b1111001010110111010000000111011 '
b1001011 &
#755000
0"
#760000
b1001011 *
1"
#761000
b1110101101111010101000011101011 %
b1110101101111010101000011101011 (
b1110101101111010100111001000000 '
b1001100 &
#765000
0"
#770000
b1001100 *
1"
#771000
b110011110100001110101001100111 %
b110011110100001110101001100111 (
b110011110100001110100101000001 '
b1001101 &
#775000
0"
#780000
b1001101 *
1"
#781000
b11011001000001100000000110 %
b11011001000001100000000110 (
b11011001000001011000001110 '
b1001110 &
#785000
0"
#790000
b1001110 *
1"
#791000
b11100010010100100110000111000100 %
b11100010010100100110000111000100 (
b11100010010100100101111100110111 '
b1001111 &
#795000
0"
#800000
b1001111 *
1"
#801000
b11001010000000110000110110010100 %
b11001010000000110000110110010100 (
b11001010000000110000101000001100 '
b1010000 &
#805000
0"
#810000
b1010000 *
1"
#811000
b11110101111111011010100111101011 %
b11110101111111011010100111101011 (
b11110101111111011010011110011101 '
b1010001 &
#815000
0"
#820000
b1010001 *
1"
#821000
b10000101001111110011001100001010 %
b10000101001111110011001100001010 (
b10000101001111110011000110111010 '
b1010010 &
#825000
0"
#830000
b1010010 *
1"
#831000
b11010110110110100010000110101 %
b11010110110110100010000110101 (
b11010110110110100001111110011 '
b1010011 &
#835000
0"
#840000
b1010011 *
1"
#841000
b11100111111110111100001111001111 %
b11100111111110111100001111001111 (
b11100111111110111100000010011000 '
b1010100 &
#845000
0"
#850000
b1010100 *
1"
#851000
b1001101111110001111001010011011 %
b1001101111110001111001010011011 (
b1001101111110001111000110111001 '
b1010101 &
#855000
0"
#860000
b1010101 *
1"
#861000
b110010110001111100000001100 %
b110010110001111100000001100 (
b110010110001111011000100110 '
b1010110 &
#865000
0"
#870000
b1010110 *
1"
#871000
b10001111111000110000110100011111 %
b10001111111000110000110100011111 (
b10001111111000110000101001101111 '
b1010111 &
#875000
0"
#880000
b1010111 *
1"
#881000
b11001010110001011111111110010101 %
b11001010110001011111111110010101 (
b11001010110001011111110111100100 '
b1011000 &
#885000
0"
#890000
b1011000 *
1"
#891000
b1101100010101001110010011011000 %
b1101100010101001110010011011000 (
b1101100010101001110001110010101 '
b1011001 &
#895000
0"
#900000
b1011001 *
1"
#901000
b11110011000111011101000111100110 %
b11110011000111011101000111100110 (
b11110011000111011100111101010010 '
b1011010 &
#905000
0"
#910000
b1011010 *
1"
#911000
b1101110000011000000000011 %
b1101110000011000000000011 (
b1101110000010111010101011 '
b1011011 &
#915000
0"
#920000
b1011011 *
1"
#921000
b11101001100001110000111111010011 %
b11101001100001110000111111010011 (
b11101001100001110000110111110000 '
b1011100 &
#925000
0"
#930000
b1011100 *
1"
#931000
b11101010110010110101101111010101 %
b11101010110010110101101111010101 (
b11101010110010110101100100110001 '
b1011101 &
#935000
0"
#940000
b1011101 *
1"
#941000
b10110001100011101110101101100011 %
b10110001100011101110101101100011 (
b10110001100011101110100100111110 '
b1011110 &
#945000
0"
#950000
b1011110 *
1"
#951000
b1011010100001101110111010110101 %
b1011010100001101110111010110101 (
b1011010100001101110110010100111 '
b1011111 &
#955000
0"
#960000
b1011111 *
1"
#961000
b1000100101101101111111010001001 %
b1000100101101101111111010001001 (
b1000100101101101111110010111100 '
b1100000 &
#965000
0"
#970000
b1100000 *
1"
#971000
b1001110000110011111000010011100 %
b1001110000110011111000010011100 (
b1001110000110011110111010001101 '
b1100001 &
#975000
0"
#980000
b1100001 *
1"
#981000
b11001010011011100011000110010100 %
b11001010011011100011000110010100 (
b11001010011011100010111111101010 '
b1100010 &
#985000
0"
#990000
b1100010 *
1"
#991000
b11100010100101010100001111000101 %
b11100010100101010100001111000101 (
b11100010100101010100000001100011 '
b1100011 &
#995000
0"
#1000000
b1100011 *
1"
#1001000
b1100100 &
